{"total":157,"pageSize":12,"pageCount":14,"data":[{"title":"幻翎","uid":"afd7f31bc36eb3808c340a10818c6101","slug":"幻翎","date":"2021-11-05T06:54:44.000Z","updated":"2021-11-05T06:54:44.646Z","comments":true,"path":"api/articles/幻翎.json","cover":"https://game.gtimg.cn/images/lol/act/img/skin/big497000.jpg","text":"背景故事&emsp;&emsp;对洛特兰部落而言，瓦斯塔亚的洛是臭名远播的捣蛋鬼，同时也是有史以来最为出色的战舞舞者。他风流潇洒，魅力无穷，同时却令人难以捉摸。在艾欧尼亚高地的居民眼中，“洛”这个名字一旦出现，就一定会带来热闹非凡的节日庆典、热火朝天的狂欢派对和杂乱无章的音乐。很...","link":"","photos":[],"count_time":{"symbolsCount":235,"symbolsTime":"1 mins."},"categories":[],"tags":[{"name":"辅助","slug":"辅助","count":35,"path":"api/tags/辅助.json"}],"author":{"name":"暮雪","slug":"blog-author","avatar":"/img/2021092617215.jpg","link":"/","description":"春光乍破遇，暮雪白头老","socials":{"github":"https://github.com/kx-860517772","twitter":"","stackoverflow":"","wechat":"/img/wechat.png","qq":"/img/qq.png","weibo":"","zhihu":"","csdn":"","juejin":"","customs":{}}}},{"title":"星界游神","uid":"2ab76892c59fd07afd9a35666c917221","slug":"星界游神","date":"2021-11-05T06:54:42.000Z","updated":"2021-11-05T06:54:42.299Z","comments":true,"path":"api/articles/星界游神.json","cover":"https://game.gtimg.cn/images/lol/act/img/skin/big432000.jpg","text":"背景故事&emsp;&emsp;巴德是星界彼端的旅者，是奇缘巧遇的使者。他艰难地维护着宇宙的平衡，从而让生命能够抵御无情的混乱。符文之地有许多人传唱关于他的歌谣，内容里流露出对他超凡本质的猜想，而所有这些歌谣都会提及同一件事：这位星界游荡者总是会被强大的魔法圣物所吸引。一群木灵欢...","link":"","photos":[],"count_time":{"symbolsCount":249,"symbolsTime":"1 mins."},"categories":[],"tags":[{"name":"法师","slug":"法师","count":61,"path":"api/tags/法师.json"},{"name":"辅助","slug":"辅助","count":35,"path":"api/tags/辅助.json"}],"author":{"name":"暮雪","slug":"blog-author","avatar":"/img/2021092617215.jpg","link":"/","description":"春光乍破遇，暮雪白头老","socials":{"github":"https://github.com/kx-860517772","twitter":"","stackoverflow":"","wechat":"/img/wechat.png","qq":"/img/qq.png","weibo":"","zhihu":"","csdn":"","juejin":"","customs":{}}}},{"title":"复仇之矛","uid":"23674fa6163bdb6d05e9c84b24c6d886","slug":"复仇之矛","date":"2021-11-05T06:54:39.000Z","updated":"2021-11-05T06:54:39.925Z","comments":true,"path":"api/articles/复仇之矛.json","cover":"https://game.gtimg.cn/images/lol/act/img/skin/big429000.jpg","text":"背景故事&emsp;&emsp;卡莉丝塔是充满复仇怨念的幽灵，是不灭的复仇之魂，是召唤自暗影岛的噩梦，专门猎杀背信弃义之人。因遭人背叛而受害的人会以血泪盼望着复仇，但只有甘愿献上自己灵魂的人，才能获得卡莉丝塔的回应。所有被卡莉丝塔盯上的人都将不可避免地遭遇不幸，因为这位死亡猎手完...","link":"","photos":[],"count_time":{"symbolsCount":218,"symbolsTime":"1 mins."},"categories":[],"tags":[{"name":"射手","slug":"射手","count":29,"path":"api/tags/射手.json"}],"author":{"name":"暮雪","slug":"blog-author","avatar":"/img/2021092617215.jpg","link":"/","description":"春光乍破遇，暮雪白头老","socials":{"github":"https://github.com/kx-860517772","twitter":"","stackoverflow":"","wechat":"/img/wechat.png","qq":"/img/qq.png","weibo":"","zhihu":"","csdn":"","juejin":"","customs":{}}}},{"title":"翠神","uid":"41c3e16ab035b7203e85cf02c0f893de","slug":"翠神","date":"2021-11-05T06:54:37.000Z","updated":"2021-11-05T06:54:37.521Z","comments":true,"path":"api/articles/翠神.json","cover":"https://game.gtimg.cn/images/lol/act/img/skin/big427000.jpg","text":"背景故事&emsp;&emsp;半人半树的艾翁•荆足常在符文之地的丛林中游荡，所经之处无不生机盎然。他知晓自然界的种种秘密，无论是飞禽走兽还是游鱼虫孑，都与他交谊深厚。在逍遥四野的途中，艾翁会向路遇的人传授奇特的智慧，或是培植丰茂的丛林。时不时地，他也会向口风不严的蝴蝶托付自己所...","link":"","photos":[],"count_time":{"symbolsCount":174,"symbolsTime":"1 mins."},"categories":[],"tags":[{"name":"法师","slug":"法师","count":61,"path":"api/tags/法师.json"},{"name":"辅助","slug":"辅助","count":35,"path":"api/tags/辅助.json"}],"author":{"name":"暮雪","slug":"blog-author","avatar":"/img/2021092617215.jpg","link":"/","description":"春光乍破遇，暮雪白头老","socials":{"github":"https://github.com/kx-860517772","twitter":"","stackoverflow":"","wechat":"/img/wechat.png","qq":"/img/qq.png","weibo":"","zhihu":"","csdn":"","juejin":"","customs":{}}}},{"title":"虚空遁地兽","uid":"3c87228a25f5418d3dfc59d6f82fe86c","slug":"虚空遁地兽","date":"2021-11-05T06:54:34.000Z","updated":"2021-11-05T06:54:34.683Z","comments":true,"path":"api/articles/虚空遁地兽.json","cover":"https://game.gtimg.cn/images/lol/act/img/skin/big421000.jpg","text":"背景故事&emsp;&emsp;作为食物链顶端的掠食者，残忍无情的虚空生物，雷克塞能够在地下挖掘隧道，偷袭并吞食毫无防备的猎物。她那永不满足的饥渴让曾经鼎盛一时的恕瑞玛帝国所在的地区满目疮痍。商人、贸易者和武装商队都会绕行百里，来躲开这些广袤的地区。一旦有人在遥远的地平线看到雷克...","link":"","photos":[],"count_time":{"symbolsCount":196,"symbolsTime":"1 mins."},"categories":[],"tags":[{"name":"战士","slug":"战士","count":68,"path":"api/tags/战士.json"}],"author":{"name":"暮雪","slug":"blog-author","avatar":"/img/2021092617215.jpg","link":"/","description":"春光乍破遇，暮雪白头老","socials":{"github":"https://github.com/kx-860517772","twitter":"","stackoverflow":"","wechat":"/img/wechat.png","qq":"/img/qq.png","weibo":"","zhihu":"","csdn":"","juejin":"","customs":{}}}},{"title":"海兽祭司","uid":"00b7d266a2994dcf1c34466a64f360d2","slug":"海兽祭司","date":"2021-11-05T06:54:32.000Z","updated":"2021-11-05T06:54:32.163Z","comments":true,"path":"api/articles/海兽祭司.json","cover":"https://game.gtimg.cn/images/lol/act/img/skin/big420000.jpg","text":"背景故事&emsp;&emsp;俄洛伊的体格强横无比，却唯独会在她的坚定信仰面前屈身。作为大海兽的先知，她挥舞着一个巨大的金色神像，将敌人的灵魂抽离体外，完全击毁他们对现实的感知。所有对“娜伽卡波洛丝的真者”发起挑战的人，很快就会发现，俄洛伊从来不单打独斗——蟒行群岛的神明会与她...","link":"","photos":[],"count_time":{"symbolsCount":182,"symbolsTime":"1 mins."},"categories":[],"tags":[{"name":"战士","slug":"战士","count":68,"path":"api/tags/战士.json"},{"name":"坦克","slug":"坦克","count":44,"path":"api/tags/坦克.json"}],"author":{"name":"暮雪","slug":"blog-author","avatar":"/img/2021092617215.jpg","link":"/","description":"春光乍破遇，暮雪白头老","socials":{"github":"https://github.com/kx-860517772","twitter":"","stackoverflow":"","wechat":"/img/wechat.png","qq":"/img/qq.png","weibo":"","zhihu":"","csdn":"","juejin":"","customs":{}}}},{"title":"魂锁典狱长","uid":"990f15912aec40747e01ebeadc2edd7a","slug":"魂锁典狱长","date":"2021-11-05T06:54:29.000Z","updated":"2021-11-05T06:54:29.747Z","comments":true,"path":"api/articles/魂锁典狱长.json","cover":"https://game.gtimg.cn/images/lol/act/img/skin/big412000.jpg","text":"背景故事&emsp;&emsp;暴虐又狡猾的锤石是一个来自暗影岛的亡灵，野心勃勃、不知疲倦。他曾经是无数奥秘的看守，在一种超越生死的力量下骨肉瓦解，而现在他则使用自己独创的钻心痛苦缓慢地折磨并击溃其他人，以此作为自己存在下去的手段。被他迫害的人需要承受远超死亡的痛苦，因为锤石会让...","link":"","photos":[],"count_time":{"symbolsCount":295,"symbolsTime":"1 mins."},"categories":[],"tags":[{"name":"辅助","slug":"辅助","count":35,"path":"api/tags/辅助.json"},{"name":"战士","slug":"战士","count":68,"path":"api/tags/战士.json"}],"author":{"name":"暮雪","slug":"blog-author","avatar":"/img/2021092617215.jpg","link":"/","description":"春光乍破遇，暮雪白头老","socials":{"github":"https://github.com/kx-860517772","twitter":"","stackoverflow":"","wechat":"/img/wechat.png","qq":"/img/qq.png","weibo":"","zhihu":"","csdn":"","juejin":"","customs":{}}}},{"title":"沙漠玫瑰","uid":"7bb4b59a9c897507bd543bb6d2325046","slug":"沙漠玫瑰","date":"2021-11-05T06:54:26.000Z","updated":"2021-11-05T06:54:27.103Z","comments":true,"path":"api/articles/沙漠玫瑰.json","cover":"https://game.gtimg.cn/images/lol/act/img/skin/big360000.jpg","text":"背景故事&emsp;&emsp;莎弥拉以寸步不让的自信直视死亡，无论走到哪里都要寻找刺激。生于恕瑞玛的她在很小的时候就被摧毁了家园，后来受到了诺克萨斯的感召，在那里，她成为了英姿飒爽的孤胆女将，专门处理最高规格的凶险任务。莎弥拉使用黑火药双枪外加一把特殊制程工艺的大刀，她在生死存...","link":"","photos":[],"count_time":{"symbolsCount":196,"symbolsTime":"1 mins."},"categories":[],"tags":[{"name":"射手","slug":"射手","count":29,"path":"api/tags/射手.json"}],"author":{"name":"暮雪","slug":"blog-author","avatar":"/img/2021092617215.jpg","link":"/","description":"春光乍破遇，暮雪白头老","socials":{"github":"https://github.com/kx-860517772","twitter":"","stackoverflow":"","wechat":"/img/wechat.png","qq":"/img/qq.png","weibo":"","zhihu":"","csdn":"","juejin":"","customs":{}}}},{"title":"魔法猫咪","uid":"3de22e0fba9fe23e7e584d26558644ec","slug":"魔法猫咪","date":"2021-11-05T06:54:24.000Z","updated":"2021-11-05T06:54:24.750Z","comments":true,"path":"api/articles/魔法猫咪.json","cover":"https://game.gtimg.cn/images/lol/act/img/skin/big350000.jpg","text":"背景故事&emsp;&emsp;作为一只来自班德尔城的魔法猫咪，悠米曾是一名约德尔魔女的守护灵，她的主人名叫诺拉。而当主人神秘消失以后，悠米就成为了《门扉魔典》的守护者，这是诺拉留下的一本有灵性的书，他们一起穿越书页中的传送门，共同寻找诺拉。渴望被宠爱的悠米在她的旅途中寻找着友善...","link":"","photos":[],"count_time":{"symbolsCount":278,"symbolsTime":"1 mins."},"categories":[],"tags":[{"name":"法师","slug":"法师","count":61,"path":"api/tags/法师.json"},{"name":"辅助","slug":"辅助","count":35,"path":"api/tags/辅助.json"}],"author":{"name":"暮雪","slug":"blog-author","avatar":"/img/2021092617215.jpg","link":"/","description":"春光乍破遇，暮雪白头老","socials":{"github":"https://github.com/kx-860517772","twitter":"","stackoverflow":"","wechat":"/img/wechat.png","qq":"/img/qq.png","weibo":"","zhihu":"","csdn":"","juejin":"","customs":{}}}},{"title":"沙漠皇帝","uid":"038b6afd5a62a04e18f33ab6bf8cdc08","slug":"沙漠皇帝","date":"2021-11-05T06:54:22.000Z","updated":"2021-11-05T06:54:22.453Z","comments":true,"path":"api/articles/沙漠皇帝.json","cover":"https://game.gtimg.cn/images/lol/act/img/skin/big268000.jpg","text":"背景故事&emsp;&emsp;阿兹尔是上古时期恕瑞玛的一位凡人皇帝，一位站在不朽神话巅峰的自豪之人。但他的狂妄引来了旁人的背叛，在最伟大胜利降临的那一刻将他杀害。而现在，数千年后，他重获新生并成为了力量无边的飞升者。阿兹尔的城市已经从黄沙之下崛起，他要让恕瑞玛恢复曾经的荣光。 ...","link":"","photos":[],"count_time":{"symbolsCount":195,"symbolsTime":"1 mins."},"categories":[],"tags":[{"name":"法师","slug":"法师","count":61,"path":"api/tags/法师.json"},{"name":"射手","slug":"射手","count":29,"path":"api/tags/射手.json"}],"author":{"name":"暮雪","slug":"blog-author","avatar":"/img/2021092617215.jpg","link":"/","description":"春光乍破遇，暮雪白头老","socials":{"github":"https://github.com/kx-860517772","twitter":"","stackoverflow":"","wechat":"/img/wechat.png","qq":"/img/qq.png","weibo":"","zhihu":"","csdn":"","juejin":"","customs":{}}}},{"title":"唤潮鲛姬","uid":"86ead745f5ef45e20b6029d7d921888f","slug":"唤潮鲛姬","date":"2021-11-05T06:54:19.000Z","updated":"2021-11-05T06:54:19.936Z","comments":true,"path":"api/articles/唤潮鲛姬.json","cover":"https://game.gtimg.cn/images/lol/act/img/skin/big267000.jpg","text":"背景故事&emsp;&emsp;娜美是一名强大年轻的瓦斯塔亚海族。当鲛人族与巨神族之间自古订立的契约被打破，她是第一个离开海洋、踏上陆地的人。她别无选择，只能挺身而出担此重任，完成神圣的仪式从而确保族人的安全。在这崭新时代的混乱浪潮中，娜美用无比的决心和无畏的斗志面对未知的明天，...","link":"","photos":[],"count_time":{"symbolsCount":246,"symbolsTime":"1 mins."},"categories":[],"tags":[{"name":"法师","slug":"法师","count":61,"path":"api/tags/法师.json"},{"name":"辅助","slug":"辅助","count":35,"path":"api/tags/辅助.json"}],"author":{"name":"暮雪","slug":"blog-author","avatar":"/img/2021092617215.jpg","link":"/","description":"春光乍破遇，暮雪白头老","socials":{"github":"https://github.com/kx-860517772","twitter":"","stackoverflow":"","wechat":"/img/wechat.png","qq":"/img/qq.png","weibo":"","zhihu":"","csdn":"","juejin":"","customs":{}}}},{"title":"暗裔剑魔","uid":"cb409c6eaf6901f4850171a89b48bde9","slug":"暗裔剑魔","date":"2021-11-05T06:54:17.000Z","updated":"2021-11-05T06:54:17.475Z","comments":true,"path":"api/articles/暗裔剑魔.json","cover":"https://game.gtimg.cn/images/lol/act/img/skin/big266000.jpg","text":"背景故事&emsp;&emsp;亚托克斯和他的同胞们曾是恕瑞玛对抗虚空之地时满载荣耀的守护者一族，最终却变成了符文之地的一个更大的威胁，并且仅被击败于被诡诈的致命巫术。但在被囚禁了数个世纪后，亚托克斯率先找到重获自由之法，那就是对那些蠢得妄图尝试挥舞那把含有他灵魂精华的神奇武器的...","link":"","photos":[],"count_time":{"symbolsCount":291,"symbolsTime":"1 mins."},"categories":[],"tags":[{"name":"战士","slug":"战士","count":68,"path":"api/tags/战士.json"},{"name":"坦克","slug":"坦克","count":44,"path":"api/tags/坦克.json"}],"author":{"name":"暮雪","slug":"blog-author","avatar":"/img/2021092617215.jpg","link":"/","description":"春光乍破遇，暮雪白头老","socials":{"github":"https://github.com/kx-860517772","twitter":"","stackoverflow":"","wechat":"/img/wechat.png","qq":"/img/qq.png","weibo":"","zhihu":"","csdn":"","juejin":"","customs":{}}}}]}