{"title":"无极剑圣","uid":"d1350c3dcdef2646140193096f18810e","slug":"无极剑圣","date":"2021-11-05T06:05:51.000Z","updated":"2021-11-05T06:05:51.909Z","comments":true,"path":"api/articles/无极剑圣.json","keywords":null,"cover":"https://game.gtimg.cn/images/lol/act/img/skin/big11000.jpg","content":"<h1 id=\"背景故事\"><a href=\"#背景故事\" class=\"headerlink\" title=\"背景故事\"></a>背景故事</h1><p>&emsp;&emsp;易师锤炼身体、磨砺心智，直至身心合一。尽管他将暴力作为不得已的选择，但他优雅迅猛的剑法总是让这一手段显得尤为快捷。作为无极之道最后的门徒，易大师致力于这个门派的传承，用七度洞悉目镜搜寻着最有资格的人，寻找潜在的新弟子。</p>\n<h1 id=\"无极剑圣\"><a href=\"#无极剑圣\" class=\"headerlink\" title=\"无极剑圣\"></a>无极剑圣</h1><p><img src=\"https://game.gtimg.cn/images/lol/act/img/skin/big11000.jpg\" alt=\"无极剑圣\"></p>\n<hr>\n<h1 id=\"暗影-易\"><a href=\"#暗影-易\" class=\"headerlink\" title=\"暗影 易\"></a>暗影 易</h1><p><img src=\"https://game.gtimg.cn/images/lol/act/img/skin/big11001.jpg\" alt=\"暗影 易\"></p>\n<hr>\n<h1 id=\"星战-易\"><a href=\"#星战-易\" class=\"headerlink\" title=\"星战 易\"></a>星战 易</h1><p><img src=\"https://game.gtimg.cn/images/lol/act/img/skin/big11002.jpg\" alt=\"星战 易\"></p>\n<hr>\n<h1 id=\"天人合一-易\"><a href=\"#天人合一-易\" class=\"headerlink\" title=\"天人合一 易\"></a>天人合一 易</h1><p><img src=\"https://game.gtimg.cn/images/lol/act/img/skin/big11003.jpg\" alt=\"天人合一 易\"></p>\n<hr>\n<h1 id=\"侍魂-易\"><a href=\"#侍魂-易\" class=\"headerlink\" title=\"侍魂 易\"></a>侍魂 易</h1><p><img src=\"https://game.gtimg.cn/images/lol/act/img/skin/big11004.jpg\" alt=\"侍魂 易\"></p>\n<hr>\n<h1 id=\"铁血剑豪-易\"><a href=\"#铁血剑豪-易\" class=\"headerlink\" title=\"铁血剑豪 易\"></a>铁血剑豪 易</h1><p><img src=\"https://game.gtimg.cn/images/lol/act/img/skin/big11005.jpg\" alt=\"铁血剑豪 易\"></p>\n<hr>\n<h1 id=\"源计划：林-易\"><a href=\"#源计划：林-易\" class=\"headerlink\" title=\"源计划：林 易\"></a>源计划：林 易</h1><p><img src=\"https://game.gtimg.cn/images/lol/act/img/skin/big11009.jpg\" alt=\"源计划：林 易\"></p>\n<hr>\n<h1 id=\"斩星魔剑-易\"><a href=\"#斩星魔剑-易\" class=\"headerlink\" title=\"斩星魔剑 易\"></a>斩星魔剑 易</h1><p><img src=\"https://game.gtimg.cn/images/lol/act/img/skin/big11010.jpg\" alt=\"斩星魔剑 易\"></p>\n<hr>\n<h1 id=\"玉剑传说-无极\"><a href=\"#玉剑传说-无极\" class=\"headerlink\" title=\"玉剑传说 无极\"></a>玉剑传说 无极</h1><p><img src=\"https://game.gtimg.cn/images/lol/act/img/skin/big11011.jpg\" alt=\"玉剑传说 无极\"></p>\n<hr>\n<h1 id=\"持胡萝卜的雪人-易\"><a href=\"#持胡萝卜的雪人-易\" class=\"headerlink\" title=\"持胡萝卜的雪人 易\"></a>持胡萝卜的雪人 易</h1><p><img src=\"https://game.gtimg.cn/images/lol/act/img/skin/big11017.jpg\" alt=\"持胡萝卜的雪人 易\"></p>\n<hr>\n<h1 id=\"腥红之月-易\"><a href=\"#腥红之月-易\" class=\"headerlink\" title=\"腥红之月 易\"></a>腥红之月 易</h1><p><img src=\"https://game.gtimg.cn/images/lol/act/img/skin/big11024.jpg\" alt=\"腥红之月 易\"></p>\n<hr>\n<h1 id=\"灵能特工-易\"><a href=\"#灵能特工-易\" class=\"headerlink\" title=\"灵能特工 易\"></a>灵能特工 易</h1><p><img src=\"https://game.gtimg.cn/images/lol/act/img/skin/big11033.jpg\" alt=\"灵能特工 易\"></p>\n","text":"背景故事&emsp;&emsp;易师锤炼身体、磨砺心智，直至身心合一。尽管他将暴力作为不得已的选择，但他优雅迅猛的剑法总是让这一手段显得尤为快捷。作为无极之道最后的门徒，易大师致力于这个门派的传承，用七度洞悉目镜搜寻着最有资格的人，寻找潜在的新弟子。 无极剑圣 暗影 易 星战 易...","link":"","photos":[],"count_time":{"symbolsCount":218,"symbolsTime":"1 mins."},"categories":[],"tags":[{"name":"战士","slug":"战士","count":68,"path":"api/tags/战士.json"},{"name":"刺客","slug":"刺客","count":40,"path":"api/tags/刺客.json"}],"toc":"<ol class=\"toc\"><li class=\"toc-item toc-level-1\"><a class=\"toc-link\" href=\"#%E8%83%8C%E6%99%AF%E6%95%85%E4%BA%8B\"><span class=\"toc-text\">背景故事</span></a></li><li class=\"toc-item toc-level-1\"><a class=\"toc-link\" href=\"#%E6%97%A0%E6%9E%81%E5%89%91%E5%9C%A3\"><span class=\"toc-text\">无极剑圣</span></a></li><li class=\"toc-item toc-level-1\"><a class=\"toc-link\" href=\"#%E6%9A%97%E5%BD%B1-%E6%98%93\"><span class=\"toc-text\">暗影 易</span></a></li><li class=\"toc-item toc-level-1\"><a class=\"toc-link\" href=\"#%E6%98%9F%E6%88%98-%E6%98%93\"><span class=\"toc-text\">星战 易</span></a></li><li class=\"toc-item toc-level-1\"><a class=\"toc-link\" href=\"#%E5%A4%A9%E4%BA%BA%E5%90%88%E4%B8%80-%E6%98%93\"><span class=\"toc-text\">天人合一 易</span></a></li><li class=\"toc-item toc-level-1\"><a class=\"toc-link\" href=\"#%E4%BE%8D%E9%AD%82-%E6%98%93\"><span class=\"toc-text\">侍魂 易</span></a></li><li class=\"toc-item toc-level-1\"><a class=\"toc-link\" href=\"#%E9%93%81%E8%A1%80%E5%89%91%E8%B1%AA-%E6%98%93\"><span class=\"toc-text\">铁血剑豪 易</span></a></li><li class=\"toc-item toc-level-1\"><a class=\"toc-link\" href=\"#%E6%BA%90%E8%AE%A1%E5%88%92%EF%BC%9A%E6%9E%97-%E6%98%93\"><span class=\"toc-text\">源计划：林 易</span></a></li><li class=\"toc-item toc-level-1\"><a class=\"toc-link\" href=\"#%E6%96%A9%E6%98%9F%E9%AD%94%E5%89%91-%E6%98%93\"><span class=\"toc-text\">斩星魔剑 易</span></a></li><li class=\"toc-item toc-level-1\"><a class=\"toc-link\" href=\"#%E7%8E%89%E5%89%91%E4%BC%A0%E8%AF%B4-%E6%97%A0%E6%9E%81\"><span class=\"toc-text\">玉剑传说 无极</span></a></li><li class=\"toc-item toc-level-1\"><a class=\"toc-link\" href=\"#%E6%8C%81%E8%83%A1%E8%90%9D%E5%8D%9C%E7%9A%84%E9%9B%AA%E4%BA%BA-%E6%98%93\"><span class=\"toc-text\">持胡萝卜的雪人 易</span></a></li><li class=\"toc-item toc-level-1\"><a class=\"toc-link\" href=\"#%E8%85%A5%E7%BA%A2%E4%B9%8B%E6%9C%88-%E6%98%93\"><span class=\"toc-text\">腥红之月 易</span></a></li><li class=\"toc-item toc-level-1\"><a class=\"toc-link\" href=\"#%E7%81%B5%E8%83%BD%E7%89%B9%E5%B7%A5-%E6%98%93\"><span class=\"toc-text\">灵能特工 易</span></a></li></ol>","author":{"name":"暮雪","slug":"blog-author","avatar":"/img/2021092617215.jpg","link":"/","description":"春光乍破遇，暮雪白头老","socials":{"github":"https://github.com/kx-860517772","twitter":"","stackoverflow":"","wechat":"/img/wechat.png","qq":"/img/qq.png","weibo":"","zhihu":"","csdn":"","juejin":"","customs":{}}},"mapped":true,"prev_post":{"title":"牛头酋长","uid":"ccc7da6abe7d72ded4656f65c0ee8a05","slug":"牛头酋长","date":"2021-11-05T06:07:12.000Z","updated":"2021-11-05T06:07:12.498Z","comments":true,"path":"api/articles/牛头酋长.json","keywords":null,"cover":"https://game.gtimg.cn/images/lol/act/img/skin/big12000.jpg","text":"背景故事&emsp;&emsp;阿利斯塔一直都是威名远扬的巨力勇士，他要为自己被屠杀的氏族向诺克萨斯帝国复仇。虽然他曾被奴役，并被迫成为斗兽场中的角斗士，但他坚不可摧的意志使他免于沦为真正的野兽。现在，挣脱了奴役枷锁的他继续以受苦之人和弱者的名义战斗。他的愤怒，还有犄角、蹄子和拳...","link":"","photos":[],"count_time":{"symbolsCount":304,"symbolsTime":"1 mins."},"categories":[],"tags":[{"name":"辅助","slug":"辅助","count":35,"path":"api/tags/辅助.json"},{"name":"坦克","slug":"坦克","count":44,"path":"api/tags/坦克.json"}],"author":{"name":"暮雪","slug":"blog-author","avatar":"/img/2021092617215.jpg","link":"/","description":"春光乍破遇，暮雪白头老","socials":{"github":"https://github.com/kx-860517772","twitter":"","stackoverflow":"","wechat":"/img/wechat.png","qq":"/img/qq.png","weibo":"","zhihu":"","csdn":"","juejin":"","customs":{}}}},"next_post":{"title":"正义天使","uid":"3adcd6749cd132ef51bc34bf00b81660","slug":"正义天使","date":"2021-11-05T05:26:22.000Z","updated":"2021-11-05T05:26:22.915Z","comments":true,"path":"api/articles/正义天使.json","keywords":null,"cover":"https://game.gtimg.cn/images/lol/act/img/skin/big10000.jpg","text":"背景故事&emsp;&emsp;在符文战争最激烈的时刻，一位巨神星灵诞下了凯尔，她传承了母亲的荣耀，在圣火飞翼的承载下为了正义而战。她和孪生妹妹莫甘娜曾是德玛西亚的保护神——但凡人反反复复的失败最终让凯尔的幻想破灭，彻底抛弃了这个国度。但关于她用火焰长剑惩罚不义之徒的传说依然在流...","link":"","photos":[],"count_time":{"symbolsCount":293,"symbolsTime":"1 mins."},"categories":[],"tags":[{"name":"辅助","slug":"辅助","count":35,"path":"api/tags/辅助.json"},{"name":"战士","slug":"战士","count":68,"path":"api/tags/战士.json"}],"author":{"name":"暮雪","slug":"blog-author","avatar":"/img/2021092617215.jpg","link":"/","description":"春光乍破遇，暮雪白头老","socials":{"github":"https://github.com/kx-860517772","twitter":"","stackoverflow":"","wechat":"/img/wechat.png","qq":"/img/qq.png","weibo":"","zhihu":"","csdn":"","juejin":"","customs":{}}}}}