{"title":"暗夜猎手","uid":"d87c35fe388594851075fadf4443c550","slug":"暗夜猎手","date":"2021-11-05T06:44:15.000Z","updated":"2021-11-05T06:44:15.481Z","comments":true,"path":"api/articles/暗夜猎手.json","keywords":null,"cover":"https://game.gtimg.cn/images/lol/act/img/skin/big67000.jpg","content":"<h1 id=\"背景故事\"><a href=\"#背景故事\" class=\"headerlink\" title=\"背景故事\"></a>背景故事</h1><p>&emsp;&emsp;肖娜·薇恩是一位无情的德玛西亚怪物猎手。终其一生，她都在寻找杀害她全家的恶魔。她的手臂上装着十字弩，心中燃烧着熊熊的复仇怒火，从暗影中射出圣银弩箭的风暴，薇恩只有在杀死那些为黑暗魔法所控制的人和生物时，才能真正感到愉悦。</p>\n<h1 id=\"暗夜猎手\"><a href=\"#暗夜猎手\" class=\"headerlink\" title=\"暗夜猎手\"></a>暗夜猎手</h1><p><img src=\"https://game.gtimg.cn/images/lol/act/img/skin/big67000.jpg\" alt=\"暗夜猎手\"></p>\n<hr>\n<h1 id=\"摩登骇客-薇恩\"><a href=\"#摩登骇客-薇恩\" class=\"headerlink\" title=\"摩登骇客 薇恩\"></a>摩登骇客 薇恩</h1><p><img src=\"https://game.gtimg.cn/images/lol/act/img/skin/big67001.jpg\" alt=\"摩登骇客 薇恩\"></p>\n<hr>\n<h1 id=\"猎天使魔女-薇恩\"><a href=\"#猎天使魔女-薇恩\" class=\"headerlink\" title=\"猎天使魔女 薇恩\"></a>猎天使魔女 薇恩</h1><p><img src=\"https://game.gtimg.cn/images/lol/act/img/skin/big67002.jpg\" alt=\"猎天使魔女 薇恩\"></p>\n<hr>\n<h1 id=\"屠龙勇士-薇恩\"><a href=\"#屠龙勇士-薇恩\" class=\"headerlink\" title=\"屠龙勇士 薇恩\"></a>屠龙勇士 薇恩</h1><p><img src=\"https://game.gtimg.cn/images/lol/act/img/skin/big67003.jpg\" alt=\"屠龙勇士 薇恩\"></p>\n<hr>\n<h1 id=\"觅心猎手-薇恩\"><a href=\"#觅心猎手-薇恩\" class=\"headerlink\" title=\"觅心猎手 薇恩\"></a>觅心猎手 薇恩</h1><p><img src=\"https://game.gtimg.cn/images/lol/act/img/skin/big67004.jpg\" alt=\"觅心猎手 薇恩\"></p>\n<hr>\n<h1 id=\"SKT-T1-薇恩\"><a href=\"#SKT-T1-薇恩\" class=\"headerlink\" title=\"SKT T1 薇恩\"></a>SKT T1 薇恩</h1><p><img src=\"https://game.gtimg.cn/images/lol/act/img/skin/big67005.jpg\" alt=\"SKT T1 薇恩\"></p>\n<hr>\n<h1 id=\"苍穹之光-薇恩\"><a href=\"#苍穹之光-薇恩\" class=\"headerlink\" title=\"苍穹之光 薇恩\"></a>苍穹之光 薇恩</h1><p><img src=\"https://game.gtimg.cn/images/lol/act/img/skin/big67006.jpg\" alt=\"苍穹之光 薇恩\"></p>\n<hr>\n<h1 id=\"摄魂使者-薇恩\"><a href=\"#摄魂使者-薇恩\" class=\"headerlink\" title=\"摄魂使者 薇恩\"></a>摄魂使者 薇恩</h1><p><img src=\"https://game.gtimg.cn/images/lol/act/img/skin/big67010.jpg\" alt=\"摄魂使者 薇恩\"></p>\n<hr>\n<h1 id=\"源计划：净化-薇恩\"><a href=\"#源计划：净化-薇恩\" class=\"headerlink\" title=\"源计划：净化 薇恩\"></a>源计划：净化 薇恩</h1><p><img src=\"https://game.gtimg.cn/images/lol/act/img/skin/big67011.jpg\" alt=\"源计划：净化 薇恩\"></p>\n<hr>\n<h1 id=\"烈焰美人-薇恩\"><a href=\"#烈焰美人-薇恩\" class=\"headerlink\" title=\"烈焰美人 薇恩\"></a>烈焰美人 薇恩</h1><p><img src=\"https://game.gtimg.cn/images/lol/act/img/skin/big67012.jpg\" alt=\"烈焰美人 薇恩\"></p>\n<hr>\n<h1 id=\"烈焰美人-薇恩-至臻\"><a href=\"#烈焰美人-薇恩-至臻\" class=\"headerlink\" title=\"烈焰美人 薇恩 至臻\"></a>烈焰美人 薇恩 至臻</h1><p><img src=\"https://game.gtimg.cn/images/lol/act/img/skin/big67013.jpg\" alt=\"烈焰美人 薇恩 至臻\"></p>\n<hr>\n<h1 id=\"灵魂莲华-薇恩\"><a href=\"#灵魂莲华-薇恩\" class=\"headerlink\" title=\"灵魂莲华 薇恩\"></a>灵魂莲华 薇恩</h1><p><img src=\"https://game.gtimg.cn/images/lol/act/img/skin/big67014.jpg\" alt=\"灵魂莲华 薇恩\"></p>\n<hr>\n<h1 id=\"FPX-薇恩\"><a href=\"#FPX-薇恩\" class=\"headerlink\" title=\"FPX 薇恩\"></a>FPX 薇恩</h1><p><img src=\"https://game.gtimg.cn/images/lol/act/img/skin/big67015.jpg\" alt=\"FPX 薇恩\"></p>\n<hr>\n<h1 id=\"光明哨兵-薇恩\"><a href=\"#光明哨兵-薇恩\" class=\"headerlink\" title=\"光明哨兵 薇恩\"></a>光明哨兵 薇恩</h1><p><img src=\"https://game.gtimg.cn/images/lol/act/img/skin/big67025.jpg\" alt=\"光明哨兵 薇恩\"></p>\n","text":"背景故事&emsp;&emsp;肖娜·薇恩是一位无情的德玛西亚怪物猎手。终其一生，她都在寻找杀害她全家的恶魔。她的手臂上装着十字弩，心中燃烧着熊熊的复仇怒火，从暗影中射出圣银弩箭的风暴，薇恩只有在杀死那些为黑暗魔法所控制的人和生物时，才能真正感到愉悦。 暗夜猎手 摩登骇客 薇恩 ...","link":"","photos":[],"count_time":{"symbolsCount":256,"symbolsTime":"1 mins."},"categories":[],"tags":[{"name":"刺客","slug":"刺客","count":40,"path":"api/tags/刺客.json"},{"name":"射手","slug":"射手","count":29,"path":"api/tags/射手.json"}],"toc":"<ol class=\"toc\"><li class=\"toc-item toc-level-1\"><a class=\"toc-link\" href=\"#%E8%83%8C%E6%99%AF%E6%95%85%E4%BA%8B\"><span class=\"toc-text\">背景故事</span></a></li><li class=\"toc-item toc-level-1\"><a class=\"toc-link\" href=\"#%E6%9A%97%E5%A4%9C%E7%8C%8E%E6%89%8B\"><span class=\"toc-text\">暗夜猎手</span></a></li><li class=\"toc-item toc-level-1\"><a class=\"toc-link\" href=\"#%E6%91%A9%E7%99%BB%E9%AA%87%E5%AE%A2-%E8%96%87%E6%81%A9\"><span class=\"toc-text\">摩登骇客 薇恩</span></a></li><li class=\"toc-item toc-level-1\"><a class=\"toc-link\" href=\"#%E7%8C%8E%E5%A4%A9%E4%BD%BF%E9%AD%94%E5%A5%B3-%E8%96%87%E6%81%A9\"><span class=\"toc-text\">猎天使魔女 薇恩</span></a></li><li class=\"toc-item toc-level-1\"><a class=\"toc-link\" href=\"#%E5%B1%A0%E9%BE%99%E5%8B%87%E5%A3%AB-%E8%96%87%E6%81%A9\"><span class=\"toc-text\">屠龙勇士 薇恩</span></a></li><li class=\"toc-item toc-level-1\"><a class=\"toc-link\" href=\"#%E8%A7%85%E5%BF%83%E7%8C%8E%E6%89%8B-%E8%96%87%E6%81%A9\"><span class=\"toc-text\">觅心猎手 薇恩</span></a></li><li class=\"toc-item toc-level-1\"><a class=\"toc-link\" href=\"#SKT-T1-%E8%96%87%E6%81%A9\"><span class=\"toc-text\">SKT T1 薇恩</span></a></li><li class=\"toc-item toc-level-1\"><a class=\"toc-link\" href=\"#%E8%8B%8D%E7%A9%B9%E4%B9%8B%E5%85%89-%E8%96%87%E6%81%A9\"><span class=\"toc-text\">苍穹之光 薇恩</span></a></li><li class=\"toc-item toc-level-1\"><a class=\"toc-link\" href=\"#%E6%91%84%E9%AD%82%E4%BD%BF%E8%80%85-%E8%96%87%E6%81%A9\"><span class=\"toc-text\">摄魂使者 薇恩</span></a></li><li class=\"toc-item toc-level-1\"><a class=\"toc-link\" href=\"#%E6%BA%90%E8%AE%A1%E5%88%92%EF%BC%9A%E5%87%80%E5%8C%96-%E8%96%87%E6%81%A9\"><span class=\"toc-text\">源计划：净化 薇恩</span></a></li><li class=\"toc-item toc-level-1\"><a class=\"toc-link\" href=\"#%E7%83%88%E7%84%B0%E7%BE%8E%E4%BA%BA-%E8%96%87%E6%81%A9\"><span class=\"toc-text\">烈焰美人 薇恩</span></a></li><li class=\"toc-item toc-level-1\"><a class=\"toc-link\" href=\"#%E7%83%88%E7%84%B0%E7%BE%8E%E4%BA%BA-%E8%96%87%E6%81%A9-%E8%87%B3%E8%87%BB\"><span class=\"toc-text\">烈焰美人 薇恩 至臻</span></a></li><li class=\"toc-item toc-level-1\"><a class=\"toc-link\" href=\"#%E7%81%B5%E9%AD%82%E8%8E%B2%E5%8D%8E-%E8%96%87%E6%81%A9\"><span class=\"toc-text\">灵魂莲华 薇恩</span></a></li><li class=\"toc-item toc-level-1\"><a class=\"toc-link\" href=\"#FPX-%E8%96%87%E6%81%A9\"><span class=\"toc-text\">FPX 薇恩</span></a></li><li class=\"toc-item toc-level-1\"><a class=\"toc-link\" href=\"#%E5%85%89%E6%98%8E%E5%93%A8%E5%85%B5-%E8%96%87%E6%81%A9\"><span class=\"toc-text\">光明哨兵 薇恩</span></a></li></ol>","author":{"name":"暮雪","slug":"blog-author","avatar":"/img/2021092617215.jpg","link":"/","description":"春光乍破遇，暮雪白头老","socials":{"github":"https://github.com/kx-860517772","twitter":"","stackoverflow":"","wechat":"/img/wechat.png","qq":"/img/qq.png","weibo":"","zhihu":"","csdn":"","juejin":"","customs":{}}},"mapped":true,"prev_post":{"title":"机械公敌","uid":"b3031ba15fcc953561236b7cffcd3e3b","slug":"机械公敌","date":"2021-11-05T06:45:35.000Z","updated":"2021-11-05T06:45:35.821Z","comments":true,"path":"api/articles/机械公敌.json","keywords":null,"cover":"https://game.gtimg.cn/images/lol/act/img/skin/big68000.jpg","text":"背景故事&emsp;&emsp;兰博是一个有脾气的约德尔青年发明家。他仅用自己的双手和一堆废铁，就造出了一架巨大的机甲，上面还搭载了电击鱼叉和燃烧火箭弹等超常规武器。虽然其他人可能对他的垃圾场发明嗤之以鼻，但兰博根本不在乎——毕竟，喷出铄金之火的枪口，在他自己手里。 机械公敌 热...","link":"","photos":[],"count_time":{"symbolsCount":193,"symbolsTime":"1 mins."},"categories":[],"tags":[{"name":"法师","slug":"法师","count":61,"path":"api/tags/法师.json"},{"name":"战士","slug":"战士","count":68,"path":"api/tags/战士.json"}],"author":{"name":"暮雪","slug":"blog-author","avatar":"/img/2021092617215.jpg","link":"/","description":"春光乍破遇，暮雪白头老","socials":{"github":"https://github.com/kx-860517772","twitter":"","stackoverflow":"","wechat":"/img/wechat.png","qq":"/img/qq.png","weibo":"","zhihu":"","csdn":"","juejin":"","customs":{}}}},"next_post":{"title":"盲僧","uid":"a786bc0e7df3ac0716d1ef4d0aecfd49","slug":"盲僧","date":"2021-11-05T06:44:13.000Z","updated":"2021-11-05T06:44:13.549Z","comments":true,"path":"api/articles/盲僧.json","keywords":null,"cover":"https://game.gtimg.cn/images/lol/act/img/skin/big64000.jpg","text":"背景故事&emsp;&emsp;李青是艾欧尼亚古老武术的大师，讲原则、重信义的他能将神龙之灵的精粹运用自如，助他面对任何挑战。虽然他多年前便已双目失明，但这位武僧依然献出自己的全部力量，用生命捍卫家园，抵御任何胆敢打破这里神圣均衡的人。所有因他安静冥想的举动而掉以轻心的敌人都将品...","link":"","photos":[],"count_time":{"symbolsCount":280,"symbolsTime":"1 mins."},"categories":[],"tags":[{"name":"战士","slug":"战士","count":68,"path":"api/tags/战士.json"},{"name":"刺客","slug":"刺客","count":40,"path":"api/tags/刺客.json"}],"author":{"name":"暮雪","slug":"blog-author","avatar":"/img/2021092617215.jpg","link":"/","description":"春光乍破遇，暮雪白头老","socials":{"github":"https://github.com/kx-860517772","twitter":"","stackoverflow":"","wechat":"/img/wechat.png","qq":"/img/qq.png","weibo":"","zhihu":"","csdn":"","juejin":"","customs":{}}}}}